{
  "part": 3,
  "title": "Approve/Reject/Enhance, In-Place Writes, Live Dashboard Refresh",
  "timestamp": "2025-10-31T12:06:00.137956",
  "status": "completed",
  "steps_completed": [
    {
      "step": "Enhanced MCP server methods",
      "description": "Updated approve, reject, and enhance methods with better error handling and audit logging",
      "status": "completed"
    },
    {
      "step": "Added API endpoints",
      "description": "Added single and bulk endpoints for approve/reject/enhance operations",
      "status": "completed"
    },
    {
      "step": "Enhanced validation list template",
      "description": "Added bulk action controls, live refresh, and WebSocket integration",
      "status": "completed"
    },
    {
      "step": "Enhanced validation detail template",
      "description": "Added action buttons and live status updates via WebSocket",
      "status": "completed"
    },
    {
      "step": "WebSocket integration",
      "description": "Added WebSocket endpoint for real-time updates and notifications",
      "status": "completed"
    },
    {
      "step": "In-place enhancement with backup",
      "description": "Enhanced MCP enhance method to create backups and write atomically",
      "status": "completed"
    }
  ],
  "features_implemented": [
    "Single validation approve/reject/enhance via API",
    "Bulk validation approve/reject/enhance via API",
    "WebSocket live refresh for dashboard",
    "Backup creation before enhancement",
    "Atomic file writing for enhancements",
    "Enhanced audit logging",
    "Dashboard action buttons",
    "Real-time status notifications"
  ],
  "api_endpoints_added": [
    "POST /api/validations/{id}/approve",
    "POST /api/validations/{id}/reject",
    "POST /api/enhance/{id}",
    "POST /api/validations/bulk/approve",
    "POST /api/validations/bulk/reject",
    "POST /api/validations/bulk/enhance",
    "WebSocket /ws/{workflow_id}"
  ],
  "files_modified": [
    "svc/mcp_server.py",
    "api/server.py",
    "templates/validations_list.html",
    "templates/validation_detail.html"
  ]
}